{
  "issue_id": "WMT-20260616172456-QEQAI2",
  "status": "created",
  "created_at": "2026-06-16T17:24:56.352Z",
  "customer_issue": "Customer requests a dark theme for the website because the current theme hurts their eyes.",
  "category": "other",
  "urgency": "low",
  "summary": "Customer requests a dark mode option for the website for eye comfort.",
  "suggested_response": "Thank you for your suggestion! We appreciate your feedback and will share your request for a dark theme with our website team."
}
